py_code_grapher/__init__.py
py_code_grapher/__main__.py
py_code_grapher-0.1.0.dist-info/METADATA
py_code_grapher-0.1.0.dist-info/WHEEL
py_code_grapher-0.1.0.dist-info/entry_points.txt
py_code_grapher-0.1.0.dist-info/RECORD
